PyMDL/Casts.py
PyMDL/Infopage.py
PyMDL/Search.py
PyMDL/SearchPeople.py
PyMDL/__init__.py
PyMDL/exceptions.py
PyMDL-1.0.1.dist-info/LICENSE
PyMDL-1.0.1.dist-info/METADATA
PyMDL-1.0.1.dist-info/WHEEL
PyMDL-1.0.1.dist-info/top_level.txt
PyMDL-1.0.1.dist-info/RECORD
