Metadata-Version: 2.1
Name: PyMDL
Version: 1.0.1
Summary: Web Scraping API to fetch data from MDL
Home-page: https://github.com/Rocker2234/Python-MDL-API
License: MIT
Keywords: MDL movie api MyDramaList
Classifier: Development Status :: 1 - Planning
Classifier: Intended Audience :: Developers
Classifier: License :: OSI Approved :: MIT License
Classifier: Operating System :: OS Independent
Classifier: Programming Language :: Python
Classifier: Programming Language :: Python :: 3 :: Only
Classifier: Topic :: Games/Entertainment
Classifier: Topic :: Internet :: WWW/HTTP
Classifier: Topic :: Internet :: WWW/HTTP :: Indexing/Search
License-File: LICENSE
Requires-Dist: beautifulsoup4
Requires-Dist: requests
Requires-Dist: lxml
